dharitri_py_sdk/__init__.py
dharitri_py_sdk/py.typed
dharitri_py_sdk/abi/__init__.py
dharitri_py_sdk/abi/abi.py
dharitri_py_sdk/abi/abi_definition.py
dharitri_py_sdk/abi/address_value.py
dharitri_py_sdk/abi/array_value.py
dharitri_py_sdk/abi/bigint_value.py
dharitri_py_sdk/abi/biguint_value.py
dharitri_py_sdk/abi/bool_value.py
dharitri_py_sdk/abi/bytes_value.py
dharitri_py_sdk/abi/code_metadata_value.py
dharitri_py_sdk/abi/codec.py
dharitri_py_sdk/abi/constants.py
dharitri_py_sdk/abi/counted_variadic_values.py
dharitri_py_sdk/abi/enum_value.py
dharitri_py_sdk/abi/explicit_enum_value.py
dharitri_py_sdk/abi/fields.py
dharitri_py_sdk/abi/interface.py
dharitri_py_sdk/abi/list_value.py
dharitri_py_sdk/abi/managed_decimal_signed_value.py
dharitri_py_sdk/abi/managed_decimal_value.py
dharitri_py_sdk/abi/multi_value.py
dharitri_py_sdk/abi/option_value.py
dharitri_py_sdk/abi/optional_value.py
dharitri_py_sdk/abi/parts.py
dharitri_py_sdk/abi/serializer.py
dharitri_py_sdk/abi/shared.py
dharitri_py_sdk/abi/small_int_values.py
dharitri_py_sdk/abi/string_value.py
dharitri_py_sdk/abi/struct_value.py
dharitri_py_sdk/abi/token_identifier_value.py
dharitri_py_sdk/abi/tuple_value.py
dharitri_py_sdk/abi/type_formula.py
dharitri_py_sdk/abi/type_formula_parser.py
dharitri_py_sdk/abi/typesystem.py
dharitri_py_sdk/abi/variadic_values.py
dharitri_py_sdk/account_management/__init__.py
dharitri_py_sdk/account_management/account_controller.py
dharitri_py_sdk/account_management/account_transactions_factory.py
dharitri_py_sdk/accounts/__init__.py
dharitri_py_sdk/accounts/account.py
dharitri_py_sdk/accounts/ledger_account.py
dharitri_py_sdk/builders/__init__.py
dharitri_py_sdk/builders/token_transfers_data_builder.py
dharitri_py_sdk/core/__init__.py
dharitri_py_sdk/core/address.py
dharitri_py_sdk/core/base_controller.py
dharitri_py_sdk/core/base_factory.py
dharitri_py_sdk/core/bech32.py
dharitri_py_sdk/core/code_metadata.py
dharitri_py_sdk/core/config.py
dharitri_py_sdk/core/constants.py
dharitri_py_sdk_test-0.0.6.dist-info/METADATA
dharitri_py_sdk_test-0.0.6.dist-info/WHEEL
dharitri_py_sdk_test-0.0.6.dist-info/licenses/LICENSE
dharitri_py_sdk_test-0.0.6.dist-info/RECORD
